mqas_dashboard/__init__.py
mqas_dashboard/app.py
mqas_dashboard/auth.py
mqas_dashboard/db.py
mqas_dashboard/jobs.py
mqas_dashboard/script.py
mqas_dashboard/workers.py
mqas_dashboard/static/css/font-awesome.min.css
mqas_dashboard/static/css/index.css
mqas_dashboard/static/css/w3.css
mqas_dashboard/static/fonts/FontAwesome.otf
mqas_dashboard/static/fonts/fontawesome-webfont.eot
mqas_dashboard/static/fonts/fontawesome-webfont.svg
mqas_dashboard/static/fonts/fontawesome-webfont.ttf
mqas_dashboard/static/fonts/fontawesome-webfont.woff
mqas_dashboard/static/fonts/fontawesome-webfont.woff2
mqas_dashboard/templates/base.html
mqas_dashboard/templates/jobs/item.html
mqas_dashboard/templates/jobs/list.html
mqas_dashboard/templates/workers/item.html
mqas_dashboard/templates/workers/list.html
mongo_qas_dashboard-0.1.18.dist-info/METADATA
mongo_qas_dashboard-0.1.18.dist-info/WHEEL
mongo_qas_dashboard-0.1.18.dist-info/entry_points.txt
mongo_qas_dashboard-0.1.18.dist-info/top_level.txt
mongo_qas_dashboard-0.1.18.dist-info/RECORD
