Metadata-Version: 2.1
Name: mongo-qas-dashboard
Version: 0.1.18
Summary: A Dashboard for the mongo-qas library
Home-page: https://github.com/giesekow/mongo-qas
Author: Giles Tetteh
Author-email: giles.tetteh@tum.de
License: UNKNOWN
Keywords: mongo,queue,schedule,rq
Platform: UNKNOWN
Classifier: Programming Language :: Python :: 3
Classifier: License :: OSI Approved :: MIT License
Classifier: Operating System :: OS Independent
Requires-Dist: pymongo
Requires-Dist: Flask
Requires-Dist: Flask-HTTPAuth
Requires-Dist: Werkzeug
